nomad/__init__.py
nomad/aflow_prototypes.py
nomad/atomutils.py
nomad/bundles.py
nomad/common.py
nomad/constants.py
nomad/doi.py
nomad/files.py
nomad/gitinfo.py
nomad/groups.py
nomad/infrastructure.py
nomad/jupyterhub_config.py
nomad/logtransfer.py
nomad/patch.py
nomad/quantum_states.py
nomad/search.py
nomad/app/__init__.py
nomad/app/h5grove_app.py
nomad/app/main.py
nomad/app/optimade_logger.py
nomad/app/dcat/__init__.py
nomad/app/dcat/common.py
nomad/app/dcat/main.py
nomad/app/dcat/mapping.py
nomad/app/dcat/routers/__init__.py
nomad/app/dcat/routers/dcat.py
nomad/app/optimade/__init__.py
nomad/app/optimade/common.py
nomad/app/optimade/elasticsearch.py
nomad/app/optimade/filterparser.py
nomad/app/optimade/optimade_config.json
nomad/app/resources/__init__.py
nomad/app/resources/common.py
nomad/app/resources/main.py
nomad/app/resources/routers/__init__.py
nomad/app/resources/routers/resources.py
nomad/app/static/__init__.py
nomad/app/static/gui/asset-manifest.json
nomad/app/static/gui/favicon-hres.png
nomad/app/static/gui/favicon.ico
nomad/app/static/gui/favicon.png
nomad/app/static/gui/index.html
nomad/app/static/gui/main.css
nomad/app/static/gui/manifest.json
nomad/app/static/gui/nomad-oasis.png
nomad/app/static/gui/nomad-text.png
nomad/app/static/gui/nomad-wo-text-hres.png
nomad/app/static/gui/nomad.afdesign
nomad/app/static/gui/nomad.png
nomad/app/static/gui/pace.css
nomad/app/static/gui/service-worker.js
nomad/app/static/gui/service-worker.js.map
nomad/app/static/gui/logo/abtem.png
nomad/app/static/gui/logo/fiji.png
nomad/app/static/gui/logo/jupyter.svg
nomad/app/static/gui/logo/nexus.png
nomad/app/static/gui/logo/nionswift.png
nomad/app/static/gui/logo/pyarpes.svg
nomad/app/static/gui/logo/pyiron.png
nomad/app/static/gui/logo/vesta.png
nomad/app/static/gui/static/css/2.dbe91c6c.chunk.css
nomad/app/static/gui/static/css/2.dbe91c6c.chunk.css.map
nomad/app/static/gui/static/css/main.ab3bb326.chunk.css
nomad/app/static/gui/static/css/main.ab3bb326.chunk.css.map
nomad_lab-1.3.17.dist-info/licenses/AUTHORS
nomad_lab-1.3.17.dist-info/licenses/LICENSE
nomad_lab-1.3.17.dist-info/METADATA
nomad_lab-1.3.17.dist-info/WHEEL
nomad_lab-1.3.17.dist-info/entry_points.txt
nomad_lab-1.3.17.dist-info/top_level.txt
nomad_lab-1.3.17.dist-info/RECORD
