Metadata-Version: 2.4
Name: nomad-lab
Version: 1.3.17
Summary: The NOvel MAterials Discovery (NOMAD) Python package
Author-email: NOMAD Laboratory <markus.scheidgen@physik.hu-berlin.de>
License: Apache-2.0
Project-URL: homepage, https://nomad-lab.eu/
Project-URL: documentation, https://nomad-lab.eu/prod/v1/docs
Project-URL: repository, https://gitlab.mpcdf.mpg.de/nomad-lab/nomad-FAIR
Requires-Python: >=3.10
License-File: LICENSE
License-File: AUTHORS
Requires-Dist: ase~=3.22.0
Requires-Dist: bitarray>=2.3.5
Requires-Dist: cachetools>=4.2.4
Requires-Dist: click>=7.1.2
Requires-Dist: docstring-parser>=0.12
Requires-Dist: elasticsearch-dsl<8,>=7
Requires-Dist: h5py>=3.6.0
Requires-Dist: httpx<0.28,>=0.23.3
Requires-Dist: jmespath>=0.10.0
Requires-Dist: jsonpath-ng
Requires-Dist: kaleido<=0.2.1
Requires-Dist: lxml>=5.2
Requires-Dist: matid>=2.1.3
Requires-Dist: msgpack>=1
Requires-Dist: msgspec
Requires-Dist: numpy<2,>=1.22.4
Requires-Dist: openpyxl
Requires-Dist: orjson>=1.0
Requires-Dist: pandas>=2
Requires-Dist: pint>=0.23
Requires-Dist: plotly<6
Requires-Dist: py-spy
Requires-Dist: pydantic>=2
Requires-Dist: pyinstrument
Requires-Dist: pymatgen>=2023.5.10
Requires-Dist: python-keycloak>=0.26.1
Requires-Dist: python-magic-bin; sys_platform == "win32"
Requires-Dist: python-magic
Requires-Dist: pytz>=2022.7.1
Requires-Dist: pyyaml>=6.0
Requires-Dist: requests<2.32.0,>=2.27.1
Requires-Dist: rfc3161ng>=2.1.3
Requires-Dist: scipy>=1.7.1
Requires-Dist: unidecode
Requires-Dist: xarray>=0.20.2
Provides-Extra: parsing
Provides-Extra: infrastructure
Requires-Dist: beautifulsoup4<=4.12.3,>=4; extra == "infrastructure"
Requires-Dist: blinker; extra == "infrastructure"
Requires-Dist: celery>=5; extra == "infrastructure"
Requires-Dist: dockerspawner; extra == "infrastructure"
Requires-Dist: fastapi; extra == "infrastructure"
Requires-Dist: gunicorn; extra == "infrastructure"
Requires-Dist: h5grove[fastapi]; extra == "infrastructure"
Requires-Dist: jupyterhub<5.0.0; extra == "infrastructure"
Requires-Dist: mongoengine; extra == "infrastructure"
Requires-Dist: oauthenticator<16.0.0; extra == "infrastructure"
Requires-Dist: optimade[mongo]; extra == "infrastructure"
Requires-Dist: pyjwt[crypto]; extra == "infrastructure"
Requires-Dist: python-logstash; extra == "infrastructure"
Requires-Dist: python-multipart; extra == "infrastructure"
Requires-Dist: rdflib==5; extra == "infrastructure"
Requires-Dist: structlog; extra == "infrastructure"
Requires-Dist: tabulate; extra == "infrastructure"
Requires-Dist: temporalio>=1.12.0; extra == "infrastructure"
Requires-Dist: uvicorn[standard]; extra == "infrastructure"
Requires-Dist: validators; extra == "infrastructure"
Requires-Dist: zipstream-ng; extra == "infrastructure"
Provides-Extra: dev
Requires-Dist: aiosmtpd>=1; extra == "dev"
Requires-Dist: devtools; extra == "dev"
Requires-Dist: essential_generators; extra == "dev"
Requires-Dist: mypy>=1.15; extra == "dev"
Requires-Dist: pytest-asyncio; extra == "dev"
Requires-Dist: pytest-cov; extra == "dev"
Requires-Dist: pytest-split; extra == "dev"
Requires-Dist: pytest-timeout; extra == "dev"
Requires-Dist: pytest-xdist; extra == "dev"
Requires-Dist: pytest; extra == "dev"
Requires-Dist: python-gitlab; extra == "dev"
Requires-Dist: ruff; extra == "dev"
Requires-Dist: setuptools>=70; extra == "dev"
Dynamic: license-file
